{"frames":{"yellow_gem_1":{"frame":{"x":31,"y":19,"w":55,"h":82},"rotated":false,"trimmed":false,"spriteSourceSize":{"x":0,"y":0,"w":55,"h":82},"sourceSize":{"w":55,"h":82}},"yellow_gem_3":{"frame":{"x":216,"y":24,"w":44,"h":72},"rotated":false,"trimmed":false,"spriteSourceSize":{"x":0,"y":0,"w":44,"h":72},"sourceSize":{"w":44,"h":72}},"yellow_gem_2":{"frame":{"x":127,"y":26,"w":47,"h":68},"rotated":false,"trimmed":false,"spriteSourceSize":{"x":0,"y":0,"w":47,"h":68},"sourceSize":{"w":47,"h":68}},"yellow_gem_4":{"frame":{"x":291,"y":33,"w":54,"h":54},"rotated":false,"trimmed":false,"spriteSourceSize":{"x":0,"y":0,"w":54,"h":54},"sourceSize":{"w":54,"h":54}},"yellow_gem_9":{"frame":{"x":627,"y":34,"w":42,"h":52},"rotated":false,"trimmed":false,"spriteSourceSize":{"x":0,"y":0,"w":42,"h":52},"sourceSize":{"w":42,"h":52}},"yellow_gem_8":{"frame":{"x":556,"y":35,"w":46,"h":51},"rotated":false,"trimmed":false,"spriteSourceSize":{"x":0,"y":0,"w":46,"h":51},"sourceSize":{"w":46,"h":51}},"yellow_gem_5":{"frame":{"x":362,"y":37,"w":47,"h":46},"rotated":false,"trimmed":false,"spriteSourceSize":{"x":0,"y":0,"w":47,"h":46},"sourceSize":{"w":47,"h":46}},"yellow_gem_6":{"frame":{"x":429,"y":37,"w":47,"h":47},"rotated":false,"trimmed":false,"spriteSourceSize":{"x":0,"y":0,"w":47,"h":47},"sourceSize":{"w":47,"h":47}},"yellow_gem_7":{"frame":{"x":489,"y":38,"w":52,"h":44},"rotated":false,"trimmed":false,"spriteSourceSize":{"x":0,"y":0,"w":52,"h":44},"sourceSize":{"w":52,"h":44}},"blue_gem_1":{"frame":{"x":31,"y":115,"w":55,"h":82},"rotated":false,"trimmed":false,"spriteSourceSize":{"x":0,"y":0,"w":55,"h":82},"sourceSize":{"w":55,"h":82}},"blue_gem_3":{"frame":{"x":216,"y":120,"w":44,"h":72},"rotated":false,"trimmed":false,"spriteSourceSize":{"x":0,"y":0,"w":44,"h":72},"sourceSize":{"w":44,"h":72}},"blue_gem_2":{"frame":{"x":127,"y":122,"w":47,"h":68},"rotated":false,"trimmed":false,"spriteSourceSize":{"x":0,"y":0,"w":47,"h":68},"sourceSize":{"w":47,"h":68}},"blue_gem_4":{"frame":{"x":291,"y":129,"w":54,"h":54},"rotated":false,"trimmed":false,"spriteSourceSize":{"x":0,"y":0,"w":54,"h":54},"sourceSize":{"w":54,"h":54}},"blue_gem_9":{"frame":{"x":627,"y":130,"w":42,"h":52},"rotated":false,"trimmed":false,"spriteSourceSize":{"x":0,"y":0,"w":42,"h":52},"sourceSize":{"w":42,"h":52}},"blue_gem_8":{"frame":{"x":556,"y":131,"w":46,"h":50},"rotated":false,"trimmed":false,"spriteSourceSize":{"x":0,"y":0,"w":46,"h":50},"sourceSize":{"w":46,"h":50}},"blue_gem_6":{"frame":{"x":429,"y":132,"w":47,"h":48},"rotated":false,"trimmed":false,"spriteSourceSize":{"x":0,"y":0,"w":47,"h":48},"sourceSize":{"w":47,"h":48}},"blue_gem_5":{"frame":{"x":362,"y":133,"w":47,"h":46},"rotated":false,"trimmed":false,"spriteSourceSize":{"x":0,"y":0,"w":47,"h":46},"sourceSize":{"w":47,"h":46}},"blue_gem_7":{"frame":{"x":489,"y":134,"w":52,"h":44},"rotated":false,"trimmed":false,"spriteSourceSize":{"x":0,"y":0,"w":52,"h":44},"sourceSize":{"w":52,"h":44}},"green_gem_1":{"frame":{"x":31,"y":211,"w":55,"h":82},"rotated":false,"trimmed":false,"spriteSourceSize":{"x":0,"y":0,"w":55,"h":82},"sourceSize":{"w":55,"h":82}},"green_gem_3":{"frame":{"x":216,"y":216,"w":44,"h":72},"rotated":false,"trimmed":false,"spriteSourceSize":{"x":0,"y":0,"w":44,"h":72},"sourceSize":{"w":44,"h":72}},"green_gem_2":{"frame":{"x":127,"y":218,"w":47,"h":68},"rotated":false,"trimmed":false,"spriteSourceSize":{"x":0,"y":0,"w":47,"h":68},"sourceSize":{"w":47,"h":68}},"green_gem_4":{"frame":{"x":291,"y":225,"w":54,"h":54},"rotated":false,"trimmed":false,"spriteSourceSize":{"x":0,"y":0,"w":54,"h":54},"sourceSize":{"w":54,"h":54}},"green_gem_9":{"frame":{"x":620,"y":226,"w":42,"h":52},"rotated":false,"trimmed":false,"spriteSourceSize":{"x":0,"y":0,"w":42,"h":52},"sourceSize":{"w":42,"h":52}},"green_gem_8":{"frame":{"x":556,"y":227,"w":46,"h":50},"rotated":false,"trimmed":false,"spriteSourceSize":{"x":0,"y":0,"w":46,"h":50},"sourceSize":{"w":46,"h":50}},"green_gem_6":{"frame":{"x":429,"y":228,"w":47,"h":48},"rotated":false,"trimmed":false,"spriteSourceSize":{"x":0,"y":0,"w":47,"h":48},"sourceSize":{"w":47,"h":48}},"green_gem_5":{"frame":{"x":362,"y":229,"w":47,"h":46},"rotated":false,"trimmed":false,"spriteSourceSize":{"x":0,"y":0,"w":47,"h":46},"sourceSize":{"w":47,"h":46}},"green_gem_7":{"frame":{"x":489,"y":230,"w":52,"h":44},"rotated":false,"trimmed":false,"spriteSourceSize":{"x":0,"y":0,"w":52,"h":44},"sourceSize":{"w":52,"h":44}},"red_gem_1":{"frame":{"x":31,"y":307,"w":55,"h":82},"rotated":false,"trimmed":false,"spriteSourceSize":{"x":0,"y":0,"w":55,"h":82},"sourceSize":{"w":55,"h":82}},"red_gem_3":{"frame":{"x":216,"y":312,"w":44,"h":72},"rotated":false,"trimmed":false,"spriteSourceSize":{"x":0,"y":0,"w":44,"h":72},"sourceSize":{"w":44,"h":72}},"red_gem_2":{"frame":{"x":127,"y":314,"w":47,"h":68},"rotated":false,"trimmed":false,"spriteSourceSize":{"x":0,"y":0,"w":47,"h":68},"sourceSize":{"w":47,"h":68}},"red_gem_4":{"frame":{"x":291,"y":321,"w":54,"h":54},"rotated":false,"trimmed":false,"spriteSourceSize":{"x":0,"y":0,"w":54,"h":54},"sourceSize":{"w":54,"h":54}},"red_gem_9":{"frame":{"x":627,"y":322,"w":42,"h":52},"rotated":false,"trimmed":false,"spriteSourceSize":{"x":0,"y":0,"w":42,"h":52},"sourceSize":{"w":42,"h":52}},"red_gem_6":{"frame":{"x":426,"y":323,"w":50,"h":50},"rotated":false,"trimmed":false,"spriteSourceSize":{"x":0,"y":0,"w":50,"h":50},"sourceSize":{"w":50,"h":50}},"red_gem_8":{"frame":{"x":556,"y":323,"w":46,"h":50},"rotated":false,"trimmed":false,"spriteSourceSize":{"x":0,"y":0,"w":46,"h":50},"sourceSize":{"w":46,"h":50}},"red_gem_5":{"frame":{"x":362,"y":325,"w":47,"h":46},"rotated":false,"trimmed":false,"spriteSourceSize":{"x":0,"y":0,"w":47,"h":46},"sourceSize":{"w":47,"h":46}},"red_gem_7":{"frame":{"x":489,"y":326,"w":52,"h":44},"rotated":false,"trimmed":false,"spriteSourceSize":{"x":0,"y":0,"w":52,"h":44},"sourceSize":{"w":52,"h":44}},"purple_gem_1":{"frame":{"x":31,"y":403,"w":55,"h":82},"rotated":false,"trimmed":false,"spriteSourceSize":{"x":0,"y":0,"w":55,"h":82},"sourceSize":{"w":55,"h":82}},"purple_gem_3":{"frame":{"x":216,"y":408,"w":44,"h":72},"rotated":false,"trimmed":false,"spriteSourceSize":{"x":0,"y":0,"w":44,"h":72},"sourceSize":{"w":44,"h":72}},"purple_gem_2":{"frame":{"x":127,"y":410,"w":47,"h":68},"rotated":false,"trimmed":false,"spriteSourceSize":{"x":0,"y":0,"w":47,"h":68},"sourceSize":{"w":47,"h":68}},"purple_gem_4":{"frame":{"x":291,"y":417,"w":54,"h":54},"rotated":false,"trimmed":false,"spriteSourceSize":{"x":0,"y":0,"w":54,"h":54},"sourceSize":{"w":54,"h":54}},"purple_gem_8":{"frame":{"x":556,"y":418,"w":46,"h":51},"rotated":false,"trimmed":false,"spriteSourceSize":{"x":0,"y":0,"w":46,"h":51},"sourceSize":{"w":46,"h":51}},"purple_gem_9":{"frame":{"x":627,"y":418,"w":42,"h":52},"rotated":false,"trimmed":false,"spriteSourceSize":{"x":0,"y":0,"w":42,"h":52},"sourceSize":{"w":42,"h":52}},"purple_gem_6":{"frame":{"x":426,"y":419,"w":50,"h":50},"rotated":false,"trimmed":false,"spriteSourceSize":{"x":0,"y":0,"w":50,"h":50},"sourceSize":{"w":50,"h":50}},"purple_gem_5":{"frame":{"x":362,"y":421,"w":47,"h":46},"rotated":false,"trimmed":false,"spriteSourceSize":{"x":0,"y":0,"w":47,"h":46},"sourceSize":{"w":47,"h":46}},"purple_gem_7":{"frame":{"x":489,"y":422,"w":52,"h":44},"rotated":false,"trimmed":false,"spriteSourceSize":{"x":0,"y":0,"w":52,"h":44},"sourceSize":{"w":52,"h":44}},"pink_gem_1":{"frame":{"x":31,"y":499,"w":55,"h":82},"rotated":false,"trimmed":false,"spriteSourceSize":{"x":0,"y":0,"w":55,"h":82},"sourceSize":{"w":55,"h":82}},"pink_gem_3":{"frame":{"x":216,"y":504,"w":44,"h":72},"rotated":false,"trimmed":false,"spriteSourceSize":{"x":0,"y":0,"w":44,"h":72},"sourceSize":{"w":44,"h":72}},"pink_gem_2":{"frame":{"x":127,"y":506,"w":47,"h":68},"rotated":false,"trimmed":false,"spriteSourceSize":{"x":0,"y":0,"w":47,"h":68},"sourceSize":{"w":47,"h":68}},"pink_gem_4":{"frame":{"x":291,"y":513,"w":54,"h":54},"rotated":false,"trimmed":false,"spriteSourceSize":{"x":0,"y":0,"w":54,"h":54},"sourceSize":{"w":54,"h":54}},"pink_gem_8":{"frame":{"x":556,"y":514,"w":46,"h":51},"rotated":false,"trimmed":false,"spriteSourceSize":{"x":0,"y":0,"w":46,"h":51},"sourceSize":{"w":46,"h":51}},"pink_gem_9":{"frame":{"x":627,"y":514,"w":42,"h":52},"rotated":false,"trimmed":false,"spriteSourceSize":{"x":0,"y":0,"w":42,"h":52},"sourceSize":{"w":42,"h":52}},"pink_gem_6":{"frame":{"x":426,"y":515,"w":50,"h":50},"rotated":false,"trimmed":false,"spriteSourceSize":{"x":0,"y":0,"w":50,"h":50},"sourceSize":{"w":50,"h":50}},"pink_gem_5":{"frame":{"x":362,"y":517,"w":47,"h":46},"rotated":false,"trimmed":false,"spriteSourceSize":{"x":0,"y":0,"w":47,"h":46},"sourceSize":{"w":47,"h":46}},"pink_gem_7":{"frame":{"x":489,"y":518,"w":52,"h":44},"rotated":false,"trimmed":false,"spriteSourceSize":{"x":0,"y":0,"w":52,"h":44},"sourceSize":{"w":52,"h":44}}},"meta":{"app":"https://www.leshylabs.com/apps/sstool/","version":"Leshy SpriteSheet Tool v0.8.4","image":"spritesheet.png","size":{"w":700,"h":600},"scale":1}}